machinic-0.1.4.dist-info/METADATA
machinic-0.1.4.dist-info/WHEEL
machinic-0.1.4.dist-info/entry_points.txt
machinic-0.1.4.dist-info/licenses/LICENSE
machinic/__init__.py
machinic/__main__.py
machinic/fn/__init__.py
machinic/fn/_functools.py
machinic/fs/__init__.py
machinic/guard/__init__.py
machinic/io/__init__.py
machinic/io/_auto.py
machinic/io/_binary.py
machinic/io/_json.py
machinic/io/_jsonc.py
machinic/io/_jsonl.py
machinic/io/_text.py
machinic/io/_toml.py
machinic/io/_yaml.py
machinic/io/todo/_7z.py
machinic/io/todo/_csv.py
machinic/io/todo/_html.py
machinic/io/todo/_jpeg.py
machinic/io/todo/_jsonschema.py
machinic/io/todo/_md.py
machinic/io/todo/_npz.py
machinic/io/todo/_png.py
machinic/io/todo/_svg.py
machinic/io/todo/_tsv.py
machinic/io/todo/_xls.py
machinic/io/todo/_xlsb.py
machinic/io/todo/_xlsx.py
machinic/io/todo/_xml.py
machinic/io/todo/_zip.py
machinic/io/todo/_zst.py
machinic/it/__init__.py
machinic/literal/__init__.py
machinic/literal/_character_encoding.py
machinic/literal/_country.py
machinic/literal/_file_extension.py
machinic/literal/_natural_language.py
machinic/literal/_synthetic_language.py
machinic/literal/_uuid.py
machinic/numbers/__init__.py
machinic/project.py
machinic/protocol/__init__.py
machinic/py.typed
machinic/pydantic/__init__.py
machinic/python/__init__.py
machinic/regex/__init__.py
machinic/regex/index.py
machinic/rs.abi3.so
machinic/rs.pyi
machinic/string/__init__.py
machinic/string/_casing.py
machinic/string/_line.py
machinic/string/_standard.py
machinic/system/__init__.py
machinic/types/__init__.py
machinic/types/_alias.py
machinic/types/_checksum.py
machinic/types/_count.py
machinic/types/_decimal.py
machinic/types/_general.py
machinic/types/_hidden.py
machinic/types/_int.py
machinic/types/_model.py
machinic/types/_numeric.py
machinic/types/_pair.py
machinic/types/_path.py
machinic/types/_secret.py
machinic/types/_source.py
machinic/types/_str.py
machinic/types/_typeshed.py
machinic/web/__init__.py
machinic-0.1.4.dist-info/RECORD
